read_logic.v
module read_logic #(parameter width = 8,parameter depth = 10)(input rrst,input rclk,input rinc,input [addr_width:0] wptr2,output reg [addr_width:0] rptr, output reg [addr_width-1:0] raddr,output reg rempty,output reg almost_empty);

localparam addr_width = $clog2(depth);

reg [addr_width:0] rcount;
reg [addr_width:0] wptr2_bin;
wire [addr_width:0] rcountnext;
wire [addr_width-1:0] raddrnext;
wire [addr_width:0] rptrnext;
wire remptynext;
wire almost_empty_next;
integer i;
always @(posedge rclk or posedge rrst) begin
    if(rrst) begin
        raddr <= {(addr_width){1'b0}};
        rptr <= {(addr_width+1){1'b0}};
        rcount <= {(addr_width+1){1'b0}};
        rempty <= 1'b0;
    end
    else begin
            rcount <= rcountnext;
            raddr <= raddrnext;
            rptr <= rptrnext;
            rempty <= remptynext;
            almost_empty <= almost_empty_next;
    end
end
assign raddrnext = rcountnext[addr_width-1:0];
assign rptrnext = rcountnext^(rcountnext>>1);
assign rcountnext = rcount + (rinc && !rempty);
assign remptynext = (rptrnext[addr_width:0] == wptr2[addr_width:0]);

always @(*) begin
    wptr2_bin[addr_width] = wptr2[addr_width];

    for (i = addr_width-1; i >= 0; i = i-1)
        wptr2_bin[i] = wptr2_bin[i+1] ^ wptr2[i];
end

assign almost_empty_next = (wptr2_bin - rcountnext) < 2;

endmodule

async_fifo.v
module async_fifo #(parameter width = 8,parameter depth = 10)(input[addr_width-1:0] waddr,input [width-1:0] data,input[addr_width-1:0] raddr,input wclk,input rclk,input w_en,output [width-1:0] op);

localparam addr_width = $clog2(depth);
reg [width-1:0] store [depth-1:0];

always @(posedge wclk) begin
    if(w_en)
        store[waddr] <= data;
end

assign op = store[raddr];

endmodule

write_logic.v
module write_logic #(parameter width = 8,parameter depth = 10)(input wrst,input wclk,input winc,input [addr_width:0] rptr2,output reg [addr_width:0] wptr, output reg [addr_width-1:0] waddr,output wen,output reg wfull,output reg almost_full);

localparam addr_width = $clog2(depth);

reg [addr_width:0] wcount;
reg [addr_width:0] rptr2_bin;
wire [addr_width:0] wcountnext;
wire [addr_width-1:0] waddrnext;
wire [addr_width:0] wptrnext;
wire wfullnext;
wire almost_full_next;

always @(posedge wclk or posedge wrst) begin
    if(wrst) begin
        waddr <= {(addr_width){1'b0}};
        wptr <= {(addr_width+1){1'b0}};
        wcount <= {(addr_width+1){1'b0}};
        wfull <= 1'b0;
    end
    else begin
            wcount <= wcountnext;
            waddr <= waddrnext;
            wptr <= wptrnext;
            wfull <= wfullnext;
            almost_full <= almost_full_next;
    end
end
assign waddrnext = wcountnext[addr_width-1:0];
assign wptrnext = wcountnext^(wcountnext>>1);
assign wcountnext = wcount + (winc && !wfull);
assign wfullnext = ((wptrnext[addr_width:addr_width-1] != rptr2[addr_width:addr_width-1])&&(wptrnext[addr_width-2:0] == rptr2[addr_width-2:0]));
assign wen = !wfull && winc;
integer i;
always @(*) begin
    rptr2_bin[addr_width] = rptr2[addr_width];

    for (i = addr_width-1; i >= 0; i = i-1)
        rptr2_bin[i] = rptr2_bin[i+1] ^ rptr2[i];
end

assign almost_full_next = (wcountnext - rptr2_bin) > depth - 3;

endmodule

sync_w_r.v
module sync_w_r #(parameter width = 8,parameter depth = 10)(input rrst,input[addr_width:0] wptr,input rclk,output reg [addr_width:0] wptr2);

localparam addr_width = $clog2(depth);

reg [addr_width:0] wptr1;

always @(posedge rclk or posedge rrst) begin
    if(rrst) begin
        wptr1 <= {(addr_width+1){1'b0}};
        wptr2 <= {(addr_width+1){1'b0}};
    end
    else 
        {wptr2,wptr1} <= {wptr1,wptr};
end

endmodule

sync_r_w.v
module sync_r_w #(parameter width = 8,parameter depth = 10)(input wrst,input[addr_width:0] rptr,input wclk,output reg [addr_width:0] rptr2);

localparam addr_width = $clog2(depth);
reg [addr_width:0] rptr1;

always @(posedge wclk or posedge wrst) begin
    if(wrst) begin
        rptr1 <= {(addr_width+1){1'b0}};
        rptr2 <= {(addr_width+1){1'b0}};
    end
    else
        {rptr2,rptr1} <= {rptr1,rptr};
end

endmodule

top.v
module top #(parameter width = 8,parameter depth = 10)(input [width-1:0] wdata,input winc,input wclk,input wrst,input rinc,input rclk,input rrst,output wfull,output rempty,output [width-1:0] rdata,output almost_full,output almost_empty);
    
    localparam addr_width = $clog2(depth);

    wire [addr_width:0] rptr,rptr2,wptr,wptr2;
    wire [addr_width-1:0] waddr,raddr;
    wire wen;

    sync_r_w #(.width(width),.depth(depth)) s1(wrst,rptr,wclk,rptr2);
    sync_w_r #(.width(width),.depth(depth)) s2(rrst,wptr,rclk,wptr2);

    write_logic #(.width(width),.depth(depth)) wl(wrst,wclk,winc,rptr2,wptr,waddr,wen,wfull,almost_full);
    async_fifo #(.width(width),.depth(depth)) fifo(waddr,wdata,raddr,wclk,rclk,wen,rdata);
    read_logic #(.width(width),.depth(depth)) rl(rrst,rclk,rinc,wptr2,rptr,raddr,rempty,almost_empty);
    
endmodule

tb.v
module tb;

reg wclk,rclk,winc,wrst,rinc,rrst;
reg [7:0] wdata;
wire [7:0] rdata;
wire wfull,rempty;
wire almost_full,almost_empty;

always #5 wclk = ~ wclk;
always #10 rclk = ~ rclk;

top #(.width(8),.depth(64)) dut(wdata,winc,wclk,wrst,rinc,rclk,rrst,wfull,rempty,rdata,almost_full,almost_empty);

initial begin
    $dumpfile("dump.vcd");
    $dumpvars(0,tb);

    wclk= 1'b0; rclk = 1'b0;
    winc = 1'b0;rinc = 1'b0;
    wdata = 8'h00;
    wrst = 1'b1;rrst = 1'b1;
    #3;
    wrst = 1'b0;rrst = 1'b0;
    
    winc = 1'b1;wdata = 8'h01;
    #5;
    winc = 1'b0;
    #5;
    winc = 1'b1;wdata = 8'h04;
    #5;
    winc = 1'b0;
    #5;
    winc = 1'b1;wdata = 8'h08;
    #5;
    winc = 1'b0;
    
    rinc = 1'b1;
    #15;
    rinc = 1'b0;
    #15;
    rinc = 1'b1;
    #15;
    rinc = 1'b0;
    #15;
    rinc = 1'b1;
    #15;
    rinc = 1'b0;

    #100;
    $finish;
end

endmodule

dump.vcd
$date
	Wed Jul 01 17:39:08 2026
$end
$version
	Icarus Verilog
$end
$timescale
	1s
$end
$scope module tb $end
$var wire 1 ! wfull $end
$var wire 1 " rempty $end
$var wire 8 # rdata [7:0] $end
$var wire 1 $ almost_full $end
$var wire 1 % almost_empty $end
$var reg 1 & rclk $end
$var reg 1 ' rinc $end
$var reg 1 ( rrst $end
$var reg 1 ) wclk $end
$var reg 8 * wdata [7:0] $end
$var reg 1 + winc $end
$var reg 1 , wrst $end
$scope module dut $end
$var wire 1 & rclk $end
$var wire 1 ' rinc $end
$var wire 1 ( rrst $end
$var wire 1 ) wclk $end
$var wire 8 - wdata [7:0] $end
$var wire 1 + winc $end
$var wire 1 , wrst $end
$var wire 7 . wptr2 [6:0] $end
$var wire 7 / wptr [6:0] $end
$var wire 1 ! wfull $end
$var wire 1 0 wen $end
$var wire 6 1 waddr [5:0] $end
$var wire 7 2 rptr2 [6:0] $end
$var wire 7 3 rptr [6:0] $end
$var wire 1 " rempty $end
$var wire 8 4 rdata [7:0] $end
$var wire 6 5 raddr [5:0] $end
$var wire 1 $ almost_full $end
$var wire 1 % almost_empty $end
$scope module fifo $end
$var wire 8 6 data [7:0] $end
$var wire 8 7 op [7:0] $end
$var wire 1 & rclk $end
$var wire 1 ) wclk $end
$var wire 6 8 waddr [5:0] $end
$var wire 1 0 w_en $end
$var wire 6 9 raddr [5:0] $end
$upscope $end
$scope module rl $end
$var wire 1 & rclk $end
$var wire 1 ' rinc $end
$var wire 7 : rptrnext [6:0] $end
$var wire 1 ( rrst $end
$var wire 7 ; wptr2 [6:0] $end
$var wire 1 < remptynext $end
$var wire 7 = rcountnext [6:0] $end
$var wire 6 > raddrnext [5:0] $end
$var wire 1 ? almost_empty_next $end
$var reg 1 % almost_empty $end
$var reg 6 @ raddr [5:0] $end
$var reg 7 A rcount [6:0] $end
$var reg 1 " rempty $end
$var reg 7 B rptr [6:0] $end
$var reg 7 C wptr2_bin [6:0] $end
$var integer 32 D i [31:0] $end
$upscope $end
$scope module s1 $end
$var wire 7 E rptr [6:0] $end
$var wire 1 ) wclk $end
$var wire 1 , wrst $end
$var reg 7 F rptr1 [6:0] $end
$var reg 7 G rptr2 [6:0] $end
$upscope $end
$scope module s2 $end
$var wire 1 & rclk $end
$var wire 1 ( rrst $end
$var wire 7 H wptr [6:0] $end
$var reg 7 I wptr1 [6:0] $end
$var reg 7 J wptr2 [6:0] $end
$upscope $end
$scope module wl $end
$var wire 7 K rptr2 [6:0] $end
$var wire 1 ) wclk $end
$var wire 1 0 wen $end
$var wire 1 L wfullnext $end
$var wire 1 + winc $end
$var wire 7 M wptrnext [6:0] $end
$var wire 1 , wrst $end
$var wire 7 N wcountnext [6:0] $end
$var wire 6 O waddrnext [5:0] $end
$var wire 1 P almost_full_next $end
$var reg 1 $ almost_full $end
$var reg 7 Q rptr2_bin [6:0] $end
$var reg 6 R waddr [5:0] $end
$var reg 7 S wcount [6:0] $end
$var reg 1 ! wfull $end
$var reg 7 T wptr [6:0] $end
$var integer 32 U i [31:0] $end
$upscope $end
$upscope $end
$upscope $end
$enddefinitions $end
#0
$dumpvars
b11111111111111111111111111111111 U
b0 T
b0 S
b0 R
b0 Q
0P
b0 O
b0 N
b0 M
0L
b0 K
b0 J
b0 I
b0 H
b0 G
b0 F
b0 E
b11111111111111111111111111111111 D
b0 C
b0 B
b0 A
b0 @
1?
b0 >
b0 =
1<
b0 ;
b0 :
b0 9
b0 8
bx 7
b0 6
b0 5
bx 4
b0 3
b0 2
b0 1
00
b0 /
b0 .
b0 -
1,
0+
b0 *
0)
1(
0'
0&
x%
x$
bx #
0"
0!
$end
#3
b1 O
b1 M
b1 N
10
b1 *
b1 -
b1 6
1+
0(
0,
#5
b10 O
b11 M
b1 #
b1 4
b1 7
0$
b1 /
b1 H
b1 T
b1 1
b1 8
b1 R
b10 N
b1 S
1)
#8
b1 O
b1 M
b1 N
00
0+
#10
1%
1"
b1 I
0)
1&
#13
b10 O
b11 M
b10 N
10
b100 *
b100 -
b100 6
1+
#15
b11 O
b10 M
b11 /
b11 H
b11 T
b10 1
b10 8
b10 R
b11 N
b10 S
1)
#18
b10 O
b11 M
b10 N
00
0+
#20
0)
0&
#23
b11 O
b10 M
b11 N
10
b1000 *
b1000 -
b1000 6
1+
#25
b100 O
b110 M
b10 /
b10 H
b10 T
b11 1
b11 8
b11 R
b100 N
b11 S
1)
#28
b11 O
b10 M
b11 N
00
1'
0+
#30
b1 C
b11111111111111111111111111111111 D
0<
b1 .
b1 ;
b1 J
b10 I
0)
1&
#35
1)
#40
0)
0&
#43
0'
#45
1)
#50
0?
b11 C
b11111111111111111111111111111111 D
0"
b10 .
b10 ;
b10 J
0)
1&
#55
1)
#58
b1 >
b1 :
b1 =
1'
#60
0)
0&
#65
1)
#70
b10 >
0<
b11 :
0%
b1 3
b1 B
b1 E
b100 #
b100 4
b100 7
b1 5
b1 9
b1 @
1?
b10 =
b1 A
0)
1&
#73
b1 >
b1 :
0?
b1 =
0'
#75
b1 F
1)
#80
0)
0&
#85
b1 Q
b11111111111111111111111111111111 U
b1 2
b1 G
b1 K
1)
#88
b10 >
0<
b11 :
1?
b10 =
1'
#90
b11 >
1<
b10 :
1%
b11 3
b11 B
b11 E
b1000 #
b1000 4
b1000 7
b10 5
b10 9
b10 @
b11 =
b10 A
0)
1&
#95
b11 F
1)
#100
0)
0&
#103
b10 >
0<
b11 :
b10 =
0'
#105
b10 Q
b11111111111111111111111111111111 U
b11 2
b11 G
b11 K
1)
